odoo/addons/account_viewer/__init__.py
odoo/addons/account_viewer/__manifest__.py
odoo/addons/account_viewer/security/account_security.xml
odoo/addons/account_viewer/security/ir.model.access.csv
odoo/addons/account_viewer/static/description/icon.png
odoo/addons/account_viewer/views/account.xml
odoo/addons/account_viewer/views/product.xml
odoo12_addon_account_viewer-12.0.1.0.1.99.dev2.dist-info/METADATA
odoo12_addon_account_viewer-12.0.1.0.1.99.dev2.dist-info/WHEEL
odoo12_addon_account_viewer-12.0.1.0.1.99.dev2.dist-info/top_level.txt
odoo12_addon_account_viewer-12.0.1.0.1.99.dev2.dist-info/RECORD
